maddy_hack/__init__.py
maddy_hack/cycle.py
maddy_hack/meeting.py
maddy_hack/weight.py
maddy_hack-0.1.0.dist-info/METADATA
maddy_hack-0.1.0.dist-info/WHEEL
maddy_hack-0.1.0.dist-info/entry_points.txt
maddy_hack-0.1.0.dist-info/top_level.txt
maddy_hack-0.1.0.dist-info/RECORD
