Metadata-Version: 2.4
Name: maddy_hack
Version: 0.1.0
Summary: A package to compute nearest meeting cells, largest cycle sums, and max weight nodes from an edge array.
Author: Mandar Kelkar
Author-email: mandarkelkar0@gmail.com
Classifier: Programming Language :: Python :: 3
Classifier: Operating System :: OS Independent
Requires-Python: >=3.6
Dynamic: author
Dynamic: author-email
Dynamic: classifier
Dynamic: requires-python
Dynamic: summary
